{
  "articles": [
    {
      "title": "SCSS for styling",
      "content": "SCSS (Sassy Cascading Style Sheets) is one of two syntaxes for the popular CSS preprocessor Sass (Syntactically Awesome Style Sheets). ",
      "category": "Programming",
      "id": "be3c",
      "authorId": 1,
      "updatedAt": "2025-04-28T10:27:58.794Z"
    },
    {
      "id": "25c2",
      "title": "React .js",
      "content": "React js is a popular framework for developing single page applications",
      "category": "Web Development",
      "authorId": 1
    }
  ],
  "users": [
    {
      "id": "1",
      "username": "johndoe",
      "name": "John Doe",
      "email": "john@example.com",
      "password": "password"
    }
  ],
  "comments": [
    {
      "id": "1",
      "postId": 1,
      "userId": 1,
      "content": "Great first post!",
      "date": "2024-03-20"
    }
  ]
}